README.md
setup.py
pgptAI.egg-info/PKG-INFO
pgptAI.egg-info/SOURCES.txt
pgptAI.egg-info/dependency_links.txt
pgptAI.egg-info/requires.txt
pgptAI.egg-info/top_level.txt
pgptai/__init__.py
pgptai/aichat/ChatCompletion.py
pgptai/aichat/Embedding.py
pgptai/aichat/__init__.py
pgptai/allai/__init__.py
pgptai/allai/_models.py
pgptai/allai/resources/__init__.py
pgptai/allai/resources/completions.py
pgptai/allai/resources/chat/__init__.py
pgptai/allai/resources/chat/chat.py
pgptai/allai/resources/chat/completions.py
pgptai/allai/types/__init__.py
pgptai/allai/types/chat/__init__.py
pgptai/allai/types/chat/chat_completions.py
pgptai/allai/types/chat/function_call.py
pgptai/allai/utils/__init__.py
pgptai/allai/utils/functions.py
pgptai/allai/utils/gemini_format.py
pgptai/audioai/__init__.py
pgptai/audioai/speech.py
pgptai/audioai/transcriptions.py
pgptai/chatglm/__init__.py
pgptai/chatglm/completions.py
pgptai/claude/__init__.py
pgptai/claude/completions.py
pgptai/claude/messages.py
pgptai/geminiai/__init__.py
pgptai/geminiai/completions.py
pgptai/geminiai/chat/__init__.py
pgptai/geminiai/chat/completions.py
pgptai/openai/__init__.py
pgptai/openai/completions.py
pgptai/openai/embeddings.py
pgptai/openai/images.py
pgptai/openai/models.py
pgptai/openai/chat/Completion.py
pgptai/openai/chat/__init__.py
pgptai/openai/chat/completions.py
pgptai/stablediffusion/__init__.py
pgptai/stablediffusion/draw.py
pgptai/textai/__init__.py
pgptai/textai/translations.py